django_adminstats/__init__.py
django_adminstats/admin.py
django_adminstats/apps.py
django_adminstats/explore.py
django_adminstats/models.py
django_adminstats/qs.py
django_adminstats/migrations/0001_initial.py
django_adminstats/migrations/0002_filters.py
django_adminstats/migrations/0003_rename_query_fields.py
django_adminstats/migrations/__init__.py
django_adminstats/registry/__init__.py
django_adminstats/registry/base.py
django_adminstats/registry/model.py
django_adminstats/registry/trackstats.py
django_adminstats/static/django_adminstats/c3.min.css
django_adminstats/static/django_adminstats/c3.min.js
django_adminstats/static/django_adminstats/chart.js
django_adminstats/static/django_adminstats/chart_form.css
django_adminstats/static/django_adminstats/chart_form.js
django_adminstats/static/django_adminstats/d3.min.js
django_adminstats/static/django_adminstats/main.css
django_adminstats/templates/django_adminstats/admin/app_index.html
django_adminstats/templates/django_adminstats/admin/index.html
django_adminstats/templates/django_adminstats/chart/change_form.html
django_adminstats/templates/django_adminstats/chart/chart.html
django_adminstats/templates/django_adminstats/chart/explore.html
django_adminstats-0.7.4.dist-info/DESCRIPTION.rst
django_adminstats-0.7.4.dist-info/METADATA
django_adminstats-0.7.4.dist-info/RECORD
django_adminstats-0.7.4.dist-info/WHEEL
django_adminstats-0.7.4.dist-info/metadata.json
django_adminstats-0.7.4.dist-info/top_level.txt
