Metadata-Version: 2.1
Name: django-adminstats
Version: 0.7.4
Summary: An adminstrative charting tool for statistics in Django
Home-page: https://gitlab.com/alantrick/django-adminstats
Author: Alan Trick
Author-email: me@alantrick.ca
License: LGPL3+
Project-URL: Bug Tracker, https://gitlab.com/alantrick/django-adminstats/issues
Project-URL: Source Code, https://gitlab.com/alantrick/django-adminstats
Keywords: charting,analytics,statistics
Platform: UNKNOWN
Classifier: Development Status :: 4 - Beta
Classifier: Environment :: Web Environment
Classifier: Framework :: Django
Classifier: Intended Audience :: Developers
Classifier: License :: OSI Approved :: GNU Lesser General Public License v3 or later (LGPLv3+)
Classifier: Operating System :: OS Independent
Classifier: Programming Language :: Python
Classifier: Programming Language :: Python :: 3.6
Classifier: Framework :: Django
Classifier: Framework :: Django :: 2.1
Classifier: Topic :: Utilities
Requires-Python: >=3.6
Provides-Extra: test
Provides-Extra: docs
